htrun/.coveragerc
htrun/__init__.py
htrun/htrun.py
htrun/host_tests/__init__.py
htrun/host_tests/base_host_test.py
htrun/host_tests/default_auto.py
htrun/host_tests/detect_auto.py
htrun/host_tests/dev_null_auto.py
htrun/host_tests/echo.py
htrun/host_tests/hello_auto.py
htrun/host_tests/rtc_auto.py
htrun/host_tests/wait_us_auto.py
htrun/host_tests_conn_proxy/__init__.py
htrun/host_tests_conn_proxy/conn_primitive.py
htrun/host_tests_conn_proxy/conn_primitive_fastmodel.py
htrun/host_tests_conn_proxy/conn_primitive_remote.py
htrun/host_tests_conn_proxy/conn_primitive_serial.py
htrun/host_tests_conn_proxy/conn_proxy.py
htrun/host_tests_logger/__init__.py
htrun/host_tests_logger/ht_logger.py
htrun/host_tests_plugins/__init__.py
htrun/host_tests_plugins/host_test_plugins.py
htrun/host_tests_plugins/host_test_registry.py
htrun/host_tests_plugins/module_copy_jn51xx.py
htrun/host_tests_plugins/module_copy_mps2.py
htrun/host_tests_plugins/module_copy_pyocd.py
htrun/host_tests_plugins/module_copy_shell.py
htrun/host_tests_plugins/module_copy_silabs.py
htrun/host_tests_plugins/module_copy_stlink.py
htrun/host_tests_plugins/module_copy_stprogrammer.py
htrun/host_tests_plugins/module_copy_to_target.py
htrun/host_tests_plugins/module_copy_ublox.py
htrun/host_tests_plugins/module_power_cycle_target.py
htrun/host_tests_plugins/module_reset_jn51xx.py
htrun/host_tests_plugins/module_reset_mps2.py
htrun/host_tests_plugins/module_reset_pyocd.py
htrun/host_tests_plugins/module_reset_silabs.py
htrun/host_tests_plugins/module_reset_stlink.py
htrun/host_tests_plugins/module_reset_target.py
htrun/host_tests_plugins/module_reset_ublox.py
htrun/host_tests_registry/__init__.py
htrun/host_tests_registry/host_registry.py
htrun/host_tests_runner/__init__.py
htrun/host_tests_runner/host_test.py
htrun/host_tests_runner/host_test_default.py
htrun/host_tests_runner/target_base.py
htrun/host_tests_toolbox/__init__.py
htrun/host_tests_toolbox/host_functional.py
greentea_host-2.0.3.dist-info/LICENSE
greentea_host-2.0.3.dist-info/METADATA
greentea_host-2.0.3.dist-info/WHEEL
greentea_host-2.0.3.dist-info/entry_points.txt
greentea_host-2.0.3.dist-info/top_level.txt
greentea_host-2.0.3.dist-info/RECORD
