Metadata-Version: 2.1
Name: greentea-host
Version: 2.0.3
Summary: greentea-host (htrun) is a command line tool that enables automated testing on embedded platforms.
Home-page: https://github.com/ARMmbed/greentea
Author: Mbed team
Author-email: support@mbed.com
Maintainer: Mbed team
Maintainer-email: support@mbed.com
License: Apache-2.0
Platform: UNKNOWN
Classifier: Development Status :: 5 - Production/Stable
Classifier: Intended Audience :: Developers
Classifier: License :: OSI Approved :: Apache Software License
Classifier: Programming Language :: Python :: 3.6
Classifier: Programming Language :: Python :: 3.7
Classifier: Programming Language :: Python :: 3.8
Classifier: Programming Language :: Python :: 3.9
Classifier: Programming Language :: Python
Classifier: Topic :: Software Development :: Build Tools
Classifier: Topic :: Software Development :: Embedded Systems
Classifier: Topic :: Software Development :: Testing
Requires-Python: >=3.5.*,<4
License-File: LICENSE
Requires-Dist: mbed-ls (>=1.8.6)
Requires-Dist: PySerial (<4.0,>=3.0)
Requires-Dist: setuptools-scm (<2,>=1.17.0)
Requires-Dist: prettytable (<3.0,>=2.0)
Requires-Dist: six (<2.0,>=1.0)
Requires-Dist: colorama (<0.5,>=0.3)
Provides-Extra: pyocd
Requires-Dist: pyocd (>=0.32.0) ; extra == 'pyocd'
